hydra_plugins/vertex_ai_custom_job_launcher/__init__.py
hydra_plugins/vertex_ai_custom_job_launcher/_core.py
hydra_plugins/vertex_ai_custom_job_launcher/_custom_job_exec.py
hydra_plugins/vertex_ai_custom_job_launcher/config.py
hydra_plugins/vertex_ai_custom_job_launcher/custom_job_launcher.py
hydra_plugins/vertex_ai_custom_job_launcher/py.typed
hydra_vertex_ai_custom_job_launcher-0.1.0rc6.dist-info/METADATA
hydra_vertex_ai_custom_job_launcher-0.1.0rc6.dist-info/WHEEL
hydra_vertex_ai_custom_job_launcher-0.1.0rc6.dist-info/top_level.txt
hydra_vertex_ai_custom_job_launcher-0.1.0rc6.dist-info/RECORD
