Metadata-Version: 2.1
Name: hydra-vertex-ai-custom-job-launcher
Version: 0.1.0rc6
Summary: Hydra Vertex AI Launcher plugin
Home-page: https://github.com/PaulBeuran/hydra-vertex-ai-custom-job-launcher
Author: Paul Beuran
Author-email: paul.beuran@outlook.fr
Classifier: License :: OSI Approved :: MIT License
Classifier: Programming Language :: Python :: 3.10
Classifier: Operating System :: OS Independent
Requires-Dist: hydra-core
Requires-Dist: google-cloud-aiplatform
Requires-Dist: fsspec
Requires-Dist: gcsfs
Requires-Dist: cloudpickle
